setup.py
django_widget_list.egg-info/PKG-INFO
django_widget_list.egg-info/SOURCES.txt
django_widget_list.egg-info/dependency_links.txt
django_widget_list.egg-info/top_level.txt
widget_list/__init__.py
widget_list/middleware.py
widget_list/widget_list.py
widget_list/static_widget_list/assets/images/add-circle-16.png
widget_list/static_widget_list/assets/images/add-circle-24.png
widget_list/static_widget_list/assets/images/arrow-16-teal.png
widget_list/static_widget_list/assets/images/arrow-16.png
widget_list/static_widget_list/assets/images/catbar-bg.png
widget_list/static_widget_list/assets/images/down-arrow-16.png
widget_list/static_widget_list/assets/images/down-arrow-24.png
widget_list/static_widget_list/assets/images/edit-16.png
widget_list/static_widget_list/assets/images/edit-24.png
widget_list/static_widget_list/assets/images/edit-34.png
widget_list/static_widget_list/assets/images/export-16.png
widget_list/static_widget_list/assets/images/export-24.png
widget_list/static_widget_list/assets/images/export-solid-16.png
widget_list/static_widget_list/assets/images/export-solid-24.png
widget_list/static_widget_list/assets/images/grad.png
widget_list/static_widget_list/assets/images/head-gradient.gif
widget_list/static_widget_list/assets/images/input_text_left.png
widget_list/static_widget_list/assets/images/input_text_right.png
widget_list/static_widget_list/assets/images/list-loader.gif
widget_list/static_widget_list/assets/images/long-text.jpg
widget_list/static_widget_list/assets/images/page-back.gif
widget_list/static_widget_list/assets/images/page-next.gif
widget_list/static_widget_list/assets/images/regular-green-leftside-regular-btn.png
widget_list/static_widget_list/assets/images/regular-green-rightside-regular-btn.png
widget_list/static_widget_list/assets/images/search-16.png
widget_list/static_widget_list/assets/images/select-multiple-left.png
widget_list/static_widget_list/assets/images/select-multiple-right.png
widget_list/static_widget_list/assets/images/select-multiple.gif
widget_list/static_widget_list/assets/images/share-arrows-24-left.png
widget_list/static_widget_list/assets/images/share-arrows-24.png
