Metadata-Version: 1.1
Name: django-widget-list
Version: 0.10.0
Summary: An Advanced and flexible ajax data grid
Home-page: https://github.com/davidrenne/widget_list
Author: David Renne
Author-email: david_renne -at- yahoo com
License: BSD
Keywords: pagination
Platform: UNKNOWN
Classifier: Development Status :: 1 - Planning
Classifier: Topic :: Database :: Front-Ends
Classifier: License :: OSI Approved :: BSD License
